native_builder/__init__.py
native_builder/cmake.py
native_builder/cmd.py
native_builder/config.py
native_builder/git.py
native_builder/project.py
native_builder/vcpkg.py
native_builder/data/vcpkg.zip
safe_config/__init__.py
safe_config/ajson.py
safe_config/api.py
safe_config/main.py
safe_config/stdlib.py
safe_config/types.py
safe_config/fable_modules/__init__.py
safe_config/fable_modules/fable_library/__init__.py
safe_config/fable_modules/fable_library/array.py
safe_config/fable_modules/fable_library/async_.py
safe_config/fable_modules/fable_library/async_builder.py
safe_config/fable_modules/fable_library/big_int.py
safe_config/fable_modules/fable_library/bit_converter.py
safe_config/fable_modules/fable_library/boolean.py
safe_config/fable_modules/fable_library/char.py
safe_config/fable_modules/fable_library/choice.py
safe_config/fable_modules/fable_library/date.py
safe_config/fable_modules/fable_library/date_offset.py
safe_config/fable_modules/fable_library/decimal.py
safe_config/fable_modules/fable_library/diagnostics.py
safe_config/fable_modules/fable_library/double.py
safe_config/fable_modules/fable_library/encoding.py
safe_config/fable_modules/fable_library/event.py
safe_config/fable_modules/fable_library/file.py
safe_config/fable_modules/fable_library/fsharp_collections.py
safe_config/fable_modules/fable_library/fsharp_core.py
safe_config/fable_modules/fable_library/global_.py
safe_config/fable_modules/fable_library/guid.py
safe_config/fable_modules/fable_library/int32.py
safe_config/fable_modules/fable_library/list.py
safe_config/fable_modules/fable_library/long.py
safe_config/fable_modules/fable_library/mailbox_processor.py
safe_config/fable_modules/fable_library/map.py
safe_config/fable_modules/fable_library/map_util.py
safe_config/fable_modules/fable_library/mutable_map.py
safe_config/fable_modules/fable_library/mutable_set.py
safe_config/fable_modules/fable_library/native.py
safe_config/fable_modules/fable_library/numeric.py
native_builder-0.2.1.dist-info/METADATA
native_builder-0.2.1.dist-info/WHEEL
native_builder-0.2.1.dist-info/entry_points.txt
native_builder-0.2.1.dist-info/top_level.txt
native_builder-0.2.1.dist-info/RECORD
