Metadata-Version: 2.1
Name: native-builder
Version: 0.2.1
Home-page: https://github.com/Suzhou-Tongyuan/NativeBuilder
Author: TongYuan
Author-email: support@tongyuan.cc
License: mit
Platform: any
Classifier: Programming Language :: Python :: 3.9
Classifier: Programming Language :: Python :: 3.10
Classifier: Programming Language :: Python :: Implementation :: CPython
Requires-Python: >=3.6.0
Requires-Dist: aiohttp
Requires-Dist: colorama
Requires-Dist: dulwich
Requires-Dist: loguru
